flashrag/__init__.py
flashrag/config/__init__.py
flashrag/config/config.py
flashrag/dataset/__init__.py
flashrag/dataset/dataset.py
flashrag/dataset/utils.py
flashrag/evaluator/__init__.py
flashrag/evaluator/_bleu.py
flashrag/evaluator/evaluator.py
flashrag/evaluator/metrics.py
flashrag/evaluator/utils.py
flashrag/generator/__init__.py
flashrag/generator/fid.py
flashrag/generator/generator.py
flashrag/generator/openai_generator.py
flashrag/generator/stop_word_criteria.py
flashrag/judger/__init__.py
flashrag/judger/judger.py
flashrag/pipeline/__init__.py
flashrag/pipeline/active_pipeline.py
flashrag/pipeline/branching_pipeline.py
flashrag/pipeline/pipeline.py
flashrag/pipeline/replug_utils.py
flashrag/prompt/__init__.py
flashrag/prompt/base_prompt.py
flashrag/prompt/selfask_examplars.py
flashrag/prompt/trace_examplars.py
flashrag/refiner/__init__.py
flashrag/refiner/kg_refiner.py
flashrag/refiner/llmlingua_compressor.py
flashrag/refiner/refiner.py
flashrag/refiner/selective_context_compressor.py
flashrag/retriever/__init__.py
flashrag/retriever/__main__.py
flashrag/retriever/encoder.py
flashrag/retriever/index_builder.py
flashrag/retriever/reranker.py
flashrag/retriever/retriever.py
flashrag/retriever/utils.py
flashrag/utils/__init__.py
flashrag/utils/constants.py
flashrag/utils/pred_parse.py
flashrag/utils/utils.py
flashrag-0.1.1.dist-info/LICENSE
flashrag-0.1.1.dist-info/METADATA
flashrag-0.1.1.dist-info/WHEEL
flashrag-0.1.1.dist-info/top_level.txt
flashrag-0.1.1.dist-info/RECORD
